_vmdetect_backend.cpython-36m-darwin.so
py_vmdetect/__init__.py
py_vmdetect/cli.py
py_vmdetect/py_vmdetect.py
py_vmdetect/vmdetect.so
py_vmdetect/src/vmdetect.cpp
py_vmdetect-0.2.5.dist-info/AUTHORS.rst
py_vmdetect-0.2.5.dist-info/LICENSE
py_vmdetect-0.2.5.dist-info/METADATA
py_vmdetect-0.2.5.dist-info/WHEEL
py_vmdetect-0.2.5.dist-info/entry_points.txt
py_vmdetect-0.2.5.dist-info/top_level.txt
py_vmdetect-0.2.5.dist-info/RECORD
