Metadata-Version: 2.1
Name: py-vmdetect
Version: 0.2.5
Summary: Python virtual machine detection tool detects virtual environment - VMWare, XEN, FreeBSD jail etc
Home-page: https://github.com/kepsic/py_vmdetect
Author: Andres Kepler
Author-email: andres@kepler.ee
License: MIT license
Keywords: py_vmdetect
Platform: UNKNOWN
Classifier: Development Status :: 2 - Pre-Alpha
Classifier: Intended Audience :: Developers
Classifier: License :: OSI Approved :: MIT License
Classifier: Natural Language :: English
Classifier: Programming Language :: Python :: 3.6
Classifier: Programming Language :: Python :: 3.7
Requires-Python: >=3.6
Requires-Dist: Click (>=6.0)
Requires-Dist: cffi (>=1.12.3)
